climatereport_zillow/__init__.py
climatereport_zillow/climatereport_zillow.py
climatereport_zillow/create_html.py
climatereport_zillow/data/fsf_fire_state_summary.csv
climatereport_zillow/data/fsf_fire_zcta_summary.csv
climatereport_zillow/data/fsf_flood_state_summary.csv
climatereport_zillow/data/fsf_flood_zcta_summary.csv
climatereport_zillow/data/fsf_heat_state_summary.csv
climatereport_zillow/data/fsf_heat_zcta_summary.csv
climatereport_zillow/extract_address.py
climatereport_zillow/google_result.py
climatereport_zillow/html_css.py
climatereport_zillow/html_style.py
climatereport_zillow/link_tests.py
climatereport_zillow/make_dataframes.py
climatereport_zillow/make_plots.py
climatereport_zillow/make_vars_zip.py
climatereport_zillow-0.1.63.dist-info/LICENSE
climatereport_zillow-0.1.63.dist-info/WHEEL
climatereport_zillow-0.1.63.dist-info/METADATA
climatereport_zillow-0.1.63.dist-info/RECORD
