Metadata-Version: 2.1
Name: climatereport-zillow
Version: 0.1.63
Summary: Zillow listings do not contain a section on the environmental risk of the property. This package compiles a report on the climate risks of the property in the zillow listing.
Home-page: https://github.com/DarciKovacs/climatereport_zillow
License: Creative Commons Attribution-NonCommercial-ShareAlike 4.0 International Public License
Author: Darci Kovacs
Requires-Python: >=3.9,<4.0
Classifier: License :: Other/Proprietary License
Classifier: Programming Language :: Python :: 3
Classifier: Programming Language :: Python :: 3.9
Classifier: Programming Language :: Python :: 3.10
Requires-Dist: bs4 (>=0.0.1,<0.0.2)
Requires-Dist: matplotlib (>=3.6.2,<4.0.0)
Requires-Dist: numpy (>=1.23.5,<2.0.0)
Requires-Dist: pandas (>=1.5.2,<2.0.0)
Requires-Dist: requests (>=2.28.1,<3.0.0)
Project-URL: Documentation, https://climatereportzillow.readthedocs.io/en/latest/index.html
Project-URL: Repository, https://github.com/DarciKovacs/climatereport_zillow
